GDI_effects/__init__ .py
GDI_effects-1.8.7.dist-info/METADATA
GDI_effects-1.8.7.dist-info/WHEEL
GDI_effects-1.8.7.dist-info/top_level.txt
GDI_effects-1.8.7.dist-info/RECORD
