Metadata-Version: 2.1
Name: GDI_effects
Version: 1.8.7
Summary: GDI_effects is a Python library that allows you to create GDI screen effects on Windows.
Author-email: coder <memecoder17@gmail.com>
Classifier: Programming Language :: Python :: 3
Classifier: Operating System :: OS Independent
Requires-Python: >=3.8
